MANIFEST.in
setup.py
mypi/__init__.py
mypi/__main__.py
mypi/api.py
mypi/package_util.py
mypi/settings.py
mypi.egg-info/PKG-INFO
mypi.egg-info/SOURCES.txt
mypi.egg-info/dependency_links.txt
mypi.egg-info/requires.txt
mypi.egg-info/top_level.txt
mypi/templates/index.html