Metadata-Version: 1.0
Name: mypi
Version: 0.0.2
Summary: An api that can automatically build and serve python packages that are hosted on github
Home-page: https://github.com/sujaymansingh/mypi
Author: Sujay Mansingh
Author-email: sujay.mansingh@gmail.com
License: LICENSE.txt
Platform: UNKNOWN
